rtsparty/__init__.py
rtsparty/stream.py
rtsparty-0.0.2.dist-info/LICENSE.md
rtsparty-0.0.2.dist-info/METADATA
rtsparty-0.0.2.dist-info/WHEEL
rtsparty-0.0.2.dist-info/top_level.txt
rtsparty-0.0.2.dist-info/RECORD
