Metadata-Version: 2.1
Name: rtsparty
Version: 0.0.2
Summary: A simple package for getting live frames from rtsp streams.
Home-page: http://github.com/ryderdamen/rtsparty
Author: Ryder Damen
Author-email: dev@ryderdamen.com
License: MIT
Keywords: rtsp stream python
Platform: UNKNOWN
Requires-Dist: opencv-contrib-python (==4.4.0.46)
